tests/__init__.py
tests/test_class_add_for_window_tools.py
tests/test_the_class_get_for_windows_tools.py
tests/test_the_class_unsorted_for_window_tools.py
tests/test_the_set_class_for_windows_tools.py
tests/test_window_asset_tkinter.py
window_asset_tkinter/__init__.py
window_asset_tkinter/__main__.py
window_asset_tkinter/calculate_window_position.py
window_asset_tkinter/capsule.py
window_asset_tkinter/err_messages.py
window_asset_tkinter/action_assets/__init__.py
window_asset_tkinter/action_assets/dict_to_micro_styler.py
window_asset_tkinter/action_assets/md_to_micro_styler.py
window_asset_tkinter/action_assets/micro_styler.py
window_asset_tkinter/action_assets/modern_entry.py
window_asset_tkinter/action_assets/mono_square_toggle_button.py
window_asset_tkinter/action_assets/password_entry.py
window_asset_tkinter/action_assets/round_toggle_switch.py
window_asset_tkinter/action_assets/square_toggle_button.py
window_asset_tkinter/window_tools/__init__.py
window_asset_tkinter/window_tools/add.py
window_asset_tkinter/window_tools/get.py
window_asset_tkinter/window_tools/internal_typing.py
window_asset_tkinter/window_tools/set.py
window_asset_tkinter/window_tools/unsorted.py
window_asset_tkinter-1.0.16.dist-info/licenses/LICENSE
window_asset_tkinter-1.0.16.dist-info/METADATA
window_asset_tkinter-1.0.16.dist-info/WHEEL
window_asset_tkinter-1.0.16.dist-info/top_level.txt
window_asset_tkinter-1.0.16.dist-info/RECORD
