Metadata-Version: 2.4
Name: window_asset_tkinter
Version: 1.0.16
Summary: A module that contains boilerplates to speed up the creation of tkinter windows
Home-page: https://github.com/Hanra-s-work/window_asset_tkinter
Author: Henry Letellier
Author-email: henrysoftwarehouse@protonmail.com
Classifier: Programming Language :: Python :: 3
Classifier: License :: OSI Approved :: MIT License
Classifier: Operating System :: OS Independent
License-File: LICENSE
Requires-Dist: tkcalendar==1.6.1
Requires-Dist: Pillow==11.3.0
Dynamic: author
Dynamic: author-email
Dynamic: classifier
Dynamic: description
Dynamic: description-content-type
Dynamic: home-page
Dynamic: license-file
Dynamic: requires-dist
Dynamic: summary
